msf_api/__init__.py
msf_api/base.py
msf_api-0.0.1.dist-info/LICENSE
msf_api-0.0.1.dist-info/METADATA
msf_api-0.0.1.dist-info/WHEEL
msf_api-0.0.1.dist-info/top_level.txt
msf_api-0.0.1.dist-info/RECORD
